toolboks_cli/__init__.py
toolboks_cli/__main__.py
toolboks_cli/_version.py
toolboks_cli/main.py
toolboks_cli-0.0.1.dist-info/LICENSE
toolboks_cli-0.0.1.dist-info/METADATA
toolboks_cli-0.0.1.dist-info/WHEEL
toolboks_cli-0.0.1.dist-info/entry_points.txt
toolboks_cli-0.0.1.dist-info/top_level.txt
toolboks_cli-0.0.1.dist-info/RECORD
