Metadata-Version: 2.1
Name: toolboks-cli
Version: 0.0.1
Summary: Command line interface for the toolboks library
Author: Mikael Tranbom
Author-email: mikael@tranbom.io
License: GPLv3
Project-URL: Homepage, https://gitlab.com/toolboks/toolboks-cli
Project-URL: Repository, https://gitlab.com/toolboks/toolboks-cli
Keywords: utility,developer tools,CLI tools
Classifier: Development Status :: 4 - Beta
Classifier: Intended Audience :: Developers
Classifier: License :: OSI Approved :: GNU General Public License v3 (GPLv3)
Classifier: Natural Language :: English
Classifier: Operating System :: OS Independent
Classifier: Programming Language :: Python
Classifier: Topic :: Software Development
Classifier: Topic :: System :: Shells
Classifier: Topic :: Utilities
Requires-Python: >=3.9
License-File: LICENSE
Requires-Dist: toolboks (==0.0.1)
